pwsh/__about__.py
pwsh/__init__.py
pwsh/_pwsh.py
pwsh/py.typed
pwsh/lib/Microsoft.Management.Infrastructure.CimCmdlets.dll
pwsh/lib/Microsoft.Management.Infrastructure.Native.dll
pwsh/lib/Microsoft.Management.Infrastructure.dll
pwsh/lib/System.Management.Automation.dll
pwsh/lib/System.Management.Automation.xml
pwsh-0.4.0.dist-info/licenses/LICENSE
pwsh-0.4.0.dist-info/METADATA
pwsh-0.4.0.dist-info/WHEEL
pwsh-0.4.0.dist-info/top_level.txt
pwsh-0.4.0.dist-info/zip-safe
pwsh-0.4.0.dist-info/RECORD
