Metadata-Version: 2.4
Name: pwsh
Version: 0.4.0
Summary: Provides API for PowerShell.
Author-email: Adam Karpierz <adam@karpierz.net>
Maintainer-email: Adam Karpierz <adam@karpierz.net>
License-Expression: Zlib
Project-URL: Homepage, https://pypi.org/project/pwsh/
Project-URL: Documentation, https://pw-sh.readthedocs.io/
Project-URL: Download, https://pypi.org/project/pwsh/
Project-URL: Source, https://github.com/karpierz/pwsh
Project-URL: Issues, https://github.com/karpierz/pwsh/issues
Keywords: powershell,pwsh
Platform: win32
Classifier: Development Status :: 5 - Production/Stable
Classifier: Intended Audience :: Developers
Classifier: Operating System :: Microsoft :: Windows
Classifier: Natural Language :: Polish
Classifier: Programming Language :: Python
Classifier: Programming Language :: Python :: 3
Classifier: Programming Language :: Python :: 3.10
Classifier: Programming Language :: Python :: 3.11
Classifier: Programming Language :: Python :: 3.12
Classifier: Programming Language :: Python :: 3.13
Classifier: Programming Language :: Python :: 3 :: Only
Classifier: Programming Language :: Python :: Implementation :: CPython
Classifier: Topic :: Software Development :: Libraries :: Python Modules
Classifier: Typing :: Typed
Requires-Python: <4.0.0,>=3.10.0
License-File: LICENSE
Requires-Dist: setuptools>=80.9.0
Requires-Dist: typing-extensions>=4.15.0
Requires-Dist: pkg-about>=2.0.0
Requires-Dist: py-utlx>=2.0.0
Requires-Dist: nocasedict>=2.1.0
Requires-Dist: zope.proxy>=7.1.0
Requires-Dist: pythonnet>=3.0.5
Requires-Dist: colored>=2.3.1
Requires-Dist: tqdm>=4.67.1
Provides-Extra: doc
Requires-Dist: sphinx>=8.1.3; extra == "doc"
Requires-Dist: sphinx-autodoc-typehints>=3.0.1; extra == "doc"
Requires-Dist: sphinx-toolbox>=4.0.0; extra == "doc"
Requires-Dist: sphinx-tabs>=3.4.5; extra == "doc"
Requires-Dist: sphinx-copybutton>=0.5.2; extra == "doc"
Requires-Dist: sphinxcontrib-spelling>=8.0.2; extra == "doc"
Requires-Dist: sphinx-lint>=1.0.2; extra == "doc"
Requires-Dist: restructuredtext-lint>=2.0.2; extra == "doc"
Requires-Dist: nbsphinx>=0.9.8; extra == "doc"
Provides-Extra: test
Requires-Dist: deepdiff>=8.6.1; extra == "test"
Requires-Dist: rich>=14.2.0; extra == "test"
Dynamic: license-file
